Outlyzer/__init__.py
Outlyzer/iqr.py
Outlyzer/least_squares.py
Outlyzer/probabilistic.py
Outlyzer/visual.py
Outlyzer/zscore.py
Outlyzer-0.0.4.dist-info/LICENSE
Outlyzer-0.0.4.dist-info/METADATA
Outlyzer-0.0.4.dist-info/WHEEL
Outlyzer-0.0.4.dist-info/top_level.txt
Outlyzer-0.0.4.dist-info/RECORD
