Metadata-Version: 2.1
Name: Outlyzer
Version: 0.0.4
Summary: Outlier detection
Home-page: https://github.com/Devparihar5/Outlyzer
Author: Devendra Parihar
Author-email: devendraparihar340@gmail.com
Keywords: outliers,outlier-detection,data-science,machine-learning,statistics,zscore,iqr,visualization
Classifier: Development Status :: 1 - Planning
Classifier: Intended Audience :: Developers
Classifier: Programming Language :: Python :: 3
Classifier: Operating System :: Unix
Classifier: Operating System :: MacOS :: MacOS X
Classifier: Operating System :: Microsoft :: Windows
License-File: LICENSE
Requires-Dist: numpy
Requires-Dist: scipy
Requires-Dist: pandas
Requires-Dist: matplotlib
